{
  "name": "My links",
  "downloads": [
    {
      "title": "Age of History 3 v 1.02 (Build 16280821)(THELASTDB)",
      "uris": [
        "magnet:?xt=urn:btih:e067a482bd0207b8e44b6c1b654c820b850d03c6&dn=Torrent%20Game&tr=udp%3A%2F%2Ftracker.openbittorrent.com%3A80%2Fannounce&tr=udp%3A%2F%2Ftracker.opentrackr.org%3A1337%2Fannounce"
      ],
      "uploadDate": "2024-11-11T21:16:00Z",
      "fileSize": "579 MB",
      "repackLinkSource": "https://thelastdb.games/38230-age-of-history-3.html"
}